{
  "title": "WAHBI Amine | Ingénieur en Électronique et Systèmes embarqués",
  "description": "Diplômé de l'ENIB et actuellement en CDI en tant qu'ingénieur en électronique et systèmes embarqués, je dispose d’une solide expérience en conception électronique et développement logiciel embarqué, acquise au cours de mon parcours professionnel et de plusieurs projets techniques réalisés. Curieux et motivé, je suis à l'écoute de nouvelles opportunités dans ce domaine à partir de septembre 2026.",
  "ogSiteName": "Portfolio WAHBI Amine",
  "shortName": "WAHBI",
  "tagline": "Électronique & Systèmes Embarqués",
  "themeStorageKey": "portfolio-theme",
  "web3formsKey": "5a55facc-416c-4a7a-b8f0-c0b5a5d27acc",
  "footerAttribution": {
    "builder": "Astro",
    "builderUrl": "https://astro.build",
    "host": "GitHub",
    "hostUrl": "https://github.com/a2wahbi"
  },
  "retroTvCount": 21,
  "seoKeywords": [
    "Ingénieur en Électronique et Systèmes embarqués",
    "Conception électronique",
    "Développement logiciel embarqué",
    "C",
    "C++",
    "Python",
    "VHDL",
    "Embedded Linux",
    "multicœurs ARM",
    "FreeRTOS",
    "ROS 2",
    "gestion multitâche",
    "STM32",
    "Raspberry Pi",
    "Arduino",
    "Silicon Labs",
    "ESP32",
    "UART",
    "SPI",
    "I2C",
    "CAN",
    "Modbus TCP/RTU",
    "BLE GATT",
    "MQTT",
    "UDP",
    "Wi-Fi",
    "KiCad",
    "Altium",
    "Eagle",
    "LTspice",
    "PSpice"
  ],
  "navExternal": [
    {
      "label": "Blog",
      "desc": "Articles techniques et retours d’expérience",
      "personalKey": "blog",
      "urlTemplate": "{value}"
    },
    {
      "label": "GitHub",
      "desc": "Code, prototypes et projets embarqués",
      "personalKey": "github",
      "urlTemplate": "https://github.com/{value}"
    },
    {
      "label": "LinkedIn",
      "desc": "Parcours professionnel et réseau",
      "personalKey": "linkedin",
      "urlTemplate": "https://linkedin.com/in/{value}"
    },
    {
      "label": "E-mail",
      "desc": "Contact direct pour projet ou opportunité",
      "personalKey": "email",
      "urlTemplate": "mailto:{value}"
    },
    {
      "label": "Téléphone",
      "desc": "Disponible sur rendez-vous",
      "personalKey": "phone",
      "urlTemplate": "tel:{value}"
    }
  ],
  "serviceSites": [
    {
      "badge": "Code source",
      "badgeColor": "#6366f1",
      "cardAccent": "#6366f1",
      "glowColor": "rgba(99, 102, 241, 0.12)",
      "iconBg": "rgba(99, 102, 241, 0.1)",
      "iconBorder": "rgba(99, 102, 241, 0.18)",
      "iconType": "web",
      "name": "GitHub",
      "url": "https://github.com/a2wahbi",
      "description": "Espace public pour consulter mes dépôts, prototypes, expérimentations et travaux liés au développement logiciel, à l’embarqué et à l’évolution de ce portfolio.",
      "features": [
        "Prototypes et projets personnels",
        "Code source du portfolio",
        "Travaux techniques versionnés"
      ],
      "ctaText": "Ouvrir GitHub"
    },
    {
      "badge": "Profil professionnel",
      "badgeColor": "#10b981",
      "cardAccent": "#10b981",
      "glowColor": "rgba(16, 185, 129, 0.15)",
      "iconBg": "rgba(16, 185, 129, 0.1)",
      "iconBorder": "rgba(16, 185, 129, 0.2)",
      "iconType": "server",
      "name": "LinkedIn",
      "url": "https://linkedin.com/in/ahmed-amine-wahbi-31787b257",
      "description": "Profil professionnel, parcours, expériences et réseau. Point d’entrée adapté pour les opportunités d’ingénierie électronique, systèmes embarqués et robotique.",
      "features": [
        "Parcours et expériences",
        "Réseau professionnel",
        "Contact pour opportunités"
      ],
      "ctaText": "Ouvrir LinkedIn"
    }
  ]
}
